setup.py
topsis/__init__.py
topsis/topsis.py
topsis_by_siddhant.egg-info/PKG-INFO
topsis_by_siddhant.egg-info/SOURCES.txt
topsis_by_siddhant.egg-info/dependency_links.txt
topsis_by_siddhant.egg-info/requires.txt
topsis_by_siddhant.egg-info/top_level.txt