Metadata-Version: 2.1
Name: topsis-by-siddhant
Version: 1.0.0
Summary: A package for Topsis technique
Home-page: UNKNOWN
Author: Siddhant Khurana
Author-email: siddhantkhurana10@gmail.com
License: UNKNOWN
Platform: UNKNOWN
Classifier: Programming Language :: Python :: 3
Classifier: License :: OSI Approved :: MIT License
Classifier: Operating System :: OS Independent
Requires-Python: >=3.6
